{
  "version": "1.0",
  "last_saved": "2026-01-08T14:21:36.675337",
  "progress": {
    "Basic": {
      "completed": [],
      "skipped": [],
      "times": {}
    },
    "Intermediate": {
      "completed": [],
      "skipped": [],
      "times": {}
    },
    "Advanced": {
      "completed": [
        23,
        24
      ],
      "skipped": [
        0,
        1,
        2,
        3,
        4,
        5,
        6,
        7,
        8,
        9,
        10,
        11,
        12,
        13,
        14,
        15,
        16,
        17,
        18,
        19,
        20,
        21,
        22
      ],
      "times": {
        "23": 73.35,
        "24": 15.79
      }
    }
  }
}